keibascraper/__init__.py
keibascraper/helper.py
keibascraper/load.py
keibascraper/parse.py
keibascraper/config/cal.json
keibascraper/config/entry.json
keibascraper/config/history.json
keibascraper/config/horse.json
keibascraper/config/odds.json
keibascraper/config/race.json
keibascraper/config/race_db.json
keibascraper/config/result.json
keibascraper-3.1.4.dist-info/licenses/LICENSE
test/__init__.py
test/test_helper.py
test/test_load_calendar.py
test/test_load_entry.py
test/test_load_horse.py
test/test_load_odds.py
test/test_load_result.py
keibascraper-3.1.4.dist-info/METADATA
keibascraper-3.1.4.dist-info/WHEEL
keibascraper-3.1.4.dist-info/top_level.txt
keibascraper-3.1.4.dist-info/RECORD
