Metadata-Version: 2.4
Name: keibascraper
Version: 3.1.4
Summary: keibascraper is a simple scraping library for netkeiba.com
Home-page: https://github.com/new-village/KeibaScraper
Author: new-village
License-File: LICENSE
Requires-Dist: requests
Requires-Dist: beautifulsoup4
Requires-Dist: jq
Dynamic: author
Dynamic: description
Dynamic: description-content-type
Dynamic: home-page
Dynamic: license-file
Dynamic: requires-dist
Dynamic: summary
